setup.py
wsgidelegator.py
wsgidelegator.egg-info/PKG-INFO
wsgidelegator.egg-info/SOURCES.txt
wsgidelegator.egg-info/dependency_links.txt
wsgidelegator.egg-info/requires.txt
wsgidelegator.egg-info/top_level.txt
wsgidelegator.egg-info/zip-safe