Metadata-Version: 1.0
Name: wsgidelegator
Version: 0.1
Summary: WSGI service that delegates to other services based on path
Home-page: http://github.com/fivehut/wsgidelegator
Author: Casey Marks
Author-email: casey@fivehut.com
License: MIT
Keywords: wsgi
Platform: UNKNOWN
Classifier: Development Status :: 3 - Alpha
Classifier: License :: OSI Approved :: MIT License
